geneticalgos/__init__.py
geneticalgos/exceptions.py
geneticalgos/ga.py
GeneticAlgos-1.0.2.dist-info/LICENSE.txt
GeneticAlgos-1.0.2.dist-info/METADATA
GeneticAlgos-1.0.2.dist-info/WHEEL
GeneticAlgos-1.0.2.dist-info/top_level.txt
GeneticAlgos-1.0.2.dist-info/RECORD
