Metadata-Version: 2.1
Name: GeneticAlgos
Version: 1.0.2
Summary: Simple and powerful Python library for creating genetic algorithms.
Home-page: https://geneticalgos.readthedocs.io/en/latest/
Author: Lukas Kozelnicky
Author-email: python@kozelnicky.com
License: MIT
Project-URL: Documentation, https://geneticalgos.readthedocs.io/en/latest/
Project-URL: Source, https://github.com/lkozelnicky/GeneticAlgos
Platform: UNKNOWN
Classifier: Development Status :: 5 - Production/Stable
Classifier: Intended Audience :: Developers
Classifier: Intended Audience :: Science/Research
Classifier: License :: OSI Approved :: MIT License
Classifier: Operating System :: OS Independent
Classifier: Programming Language :: Python :: 3.7
Classifier: Programming Language :: Python :: 3.8
Classifier: Programming Language :: Python :: 3.9
Classifier: Programming Language :: Python :: 3.10
Requires-Python: >=3.7
License-File: LICENSE.txt
Requires-Dist: numpy
